nomad_utility_workflows/__init__.py
nomad_utility_workflows/utils/__init__.py
nomad_utility_workflows/utils/core.py
nomad_utility_workflows/utils/datasets.py
nomad_utility_workflows/utils/entries.py
nomad_utility_workflows/utils/uploads.py
nomad_utility_workflows/utils/users.py
nomad_utility_workflows/utils/workflows.py
nomad_utility_workflows-0.3.0.dist-info/licenses/LICENSE
nomad_utility_workflows-0.3.0.dist-info/METADATA
nomad_utility_workflows-0.3.0.dist-info/WHEEL
nomad_utility_workflows-0.3.0.dist-info/entry_points.txt
nomad_utility_workflows-0.3.0.dist-info/top_level.txt
nomad_utility_workflows-0.3.0.dist-info/RECORD
