Metadata-Version: 2.4
Name: nomad-utility-workflows
Version: 0.3.0
Summary: A module with utilities for interacting with NOMAD via, e.g., a workflow manager.
Author-email: "Joseph F. Rudzinski" <joseph.rudzinski@physik.hu-berlin.de>
Maintainer-email: "Joseph F. Rudzinski" <joseph.rudzinski@physik.hu-berlin.de>
License: 
Project-URL: Repository, https://github.com/FAIRmat-NFDI/nomad-utility-workflows
Classifier: Intended Audience :: Developers
Classifier: Operating System :: OS Independent
Classifier: Programming Language :: Python
Classifier: Programming Language :: Python :: 3.9
Classifier: Programming Language :: Python :: 3.10
Classifier: Programming Language :: Python :: 3.11
Classifier: Programming Language :: Python :: 3.12
Classifier: License :: OSI Approved :: Apache Software License
Requires-Python: >=3.9
License-File: LICENSE
Requires-Dist: networkx
Requires-Dist: python-decouple
Requires-Dist: marshmallow>=3.23.0
Requires-Dist: marshmallow-dataclass>=8.7.1
Requires-Dist: cachetools>=5.3.2
Requires-Dist: pydantic>=2.0
Requires-Dist: requests>=2.31.0
Requires-Dist: typing-extensions>=4.12.2
Requires-Dist: pyyaml>=6.0
Requires-Dist: dotenv>=0.9.9
Provides-Extra: vis
Requires-Dist: gravis>=0.1.0; extra == "vis"
Requires-Dist: jupyter>=1.1.1; extra == "vis"
Requires-Dist: jupyterlab>=4.3.0; extra == "vis"
Requires-Dist: ipykernel>=6.29.5; extra == "vis"
Provides-Extra: dev
Requires-Dist: ruff; extra == "dev"
Requires-Dist: pytest; extra == "dev"
Requires-Dist: structlog; extra == "dev"
Dynamic: license-file
